{"id": "X5KquK93ahI", "title": "pesado-amor incondicional", "formats": [{"asr": 48000, "filesize": 1139209, "format_id": "249", "format_note": "tiny", "fps": null, "height": null, "quality": 0, "tbr": 52.353, "url": "https://rr5---sn-0opoxu-ihvr.googlevideo.com/videoplayback?expire=1670718318&ei=Dc-UY_GtPM-AsfIPuty4-AM&ip=189.173.225.87&id=o-AN502JbXx5gBx12bXj-eR-u8qZxAKw-nBrWZ3dt56oz9&itag=249&source=youtube&requiressl=yes&mh=Hg&mm=31%2C29&mn=sn-0opoxu-ihvr%2Csn-q4flrnsk&ms=au%2Crdu&mv=m&mvi=5&pl=24&pcm2=yes&initcwndbps=792500&vprv=1&mime=audio%2Fwebm&ns=0rfghrVTY7FJYMrm_ilQ2zwJ&gir=yes&clen=1139209&dur=174.081&lmt=1573658932393250&mt=1670696477&fvip=2&keepalive=yes&fexp=24001373%2C24007246&c=WEB&txp=1311222&n=CFYFrCNeVKvzRet3t&sparams=expire%2Cei%2Cip%2Cid%2Citag%2Csource%2Crequiressl%2Cpcm2%2Cvprv%2Cmime%2Cns%2Cgir%2Cclen%2Cdur%2Clmt&lsparams=mh%2Cmm%2Cmn%2Cms%2Cmv%2Cmvi%2Cpl%2Cinitcwndbps&lsig=AG3C_xAwRQIgQZw9lPBSZ1RjFltOw-U3dO-exUWdQ495IvTbsPnVJ_QCIQC8qIUdtp79QyHBKp8FhKWVIjmBQRI7-iTofhLQXspffw%3D%3D&sig=AOq0QJ8wRQIgTi_8If4AhgcouljIK5QXnfSHJgP2DgJ_f8nztt7lCAgCIQDbUgEl2vf18GEylgh0Ns939BdtaxP6qh7iKnkCbtXqmw==", "width": null, "ext": "webm", "vcodec": "none", "acodec": "opus", "abr": 52.353, "downloader_options": {"http_chunk_size": 10485760}, "container": "webm_dash", "format": "249 - audio only (tiny)", "protocol": "https", "http_headers": {"User-Agent": "Mozilla/5.0 (Windows NT 10.0; Win64; x64) AppleWebKit/537.36 (KHTML, like Gecko) Chrome/70.0.3538.116 Safari/537.36", "Accept-Charset": "ISO-8859-1,utf-8;q=0.7,*;q=0.7", "Accept": "text/html,application/xhtml+xml,application/xml;q=0.9,*/*;q=0.8", "Accept-Encoding": "gzip, deflate", "Accept-Language": "en-us,en;q=0.5"}}, {"asr": 48000, "filesize": 1496076, "format_id": "250", "format_note": "tiny", "fps": null, "height": null, "quality": 0, "tbr": 68.753, "url": "https://rr5---sn-0opoxu-ihvr.googlevideo.com/videoplayback?expire=1670718318&ei=Dc-UY_GtPM-AsfIPuty4-AM&ip=189.173.225.87&id=o-AN502JbXx5gBx12bXj-eR-u8qZxAKw-nBrWZ3dt56oz9&itag=250&source=youtube&requiressl=yes&mh=Hg&mm=31%2C29&mn=sn-0opoxu-ihvr%2Csn-q4flrnsk&ms=au%2Crdu&mv=m&mvi=5&pl=24&pcm2=yes&initcwndbps=792500&vprv=1&mime=audio%2Fwebm&ns=0rfghrVTY7FJYMrm_ilQ2zwJ&gir=yes&clen=1496076&dur=174.081&lmt=1573658930394209&mt=1670696477&fvip=2&keepalive=yes&fexp=24001373%2C24007246&c=WEB&txp=1311222&n=CFYFrCNeVKvzRet3t&sparams=expire%2Cei%2Cip%2Cid%2Citag%2Csource%2Crequiressl%2Cpcm2%2Cvprv%2Cmime%2Cns%2Cgir%2Cclen%2Cdur%2Clmt&lsparams=mh%2Cmm%2Cmn%2Cms%2Cmv%2Cmvi%2Cpl%2Cinitcwndbps&lsig=AG3C_xAwRAIgXtb54GjCoXJk_u9-c7U0E06H11nNILM09X0NKZ3CreoCIAevQPqmO4B3vXb9X2PI40q8_zmWb3n6F1A66ShP1AbW&sig=AOq0QJ8wRQIgelBKrV9JYu_Pf_gI_-hh3P4WoWSX5MLDN_Ohw2TFG0ACIQDyxZ5eeFe56BVUMuXK4KkS6zgojB7CnR1yfsnoUYkwNA==", "width": null, "ext": "webm", "vcodec": "none", "acodec": "opus", "abr": 68.753, "downloader_options": {"http_chunk_size": 10485760}, "container": "webm_dash", "format": "250 - audio only (tiny)", "protocol": "https", "http_headers": {"User-Agent": "Mozilla/5.0 (Windows NT 10.0; Win64; x64) AppleWebKit/537.36 (KHTML, like Gecko) Chrome/70.0.3538.116 Safari/537.36", "Accept-Charset": "ISO-8859-1,utf-8;q=0.7,*;q=0.7", "Accept": "text/html,application/xhtml+xml,application/xml;q=0.9,*/*;q=0.8", "Accept-Encoding": "gzip, deflate", "Accept-Language": "en-us,en;q=0.5"}}, {"asr": 44100, "filesize": 2818771, "format_id": "140", "format_note": "tiny", "fps": null, "height": null, "quality": 0, "tbr": 129.504, "url": "https://rr5---sn-0opoxu-ihvr.googlevideo.com/videoplayback?expire=1670718318&ei=Dc-UY_GtPM-AsfIPuty4-AM&ip=189.173.225.87&id=o-AN502JbXx5gBx12bXj-eR-u8qZxAKw-nBrWZ3dt56oz9&itag=140&source=youtube&requiressl=yes&mh=Hg&mm=31%2C29&mn=sn-0opoxu-ihvr%2Csn-q4flrnsk&ms=au%2Crdu&mv=m&mvi=5&pl=24&pcm2=yes&initcwndbps=792500&vprv=1&mime=audio%2Fmp4&ns=0rfghrVTY7FJYMrm_ilQ2zwJ&gir=yes&clen=2818771&dur=174.126&lmt=1573659040642366&mt=1670696477&fvip=2&keepalive=yes&fexp=24001373%2C24007246&c=WEB&txp=1311222&n=CFYFrCNeVKvzRet3t&sparams=expire%2Cei%2Cip%2Cid%2Citag%2Csource%2Crequiressl%2Cpcm2%2Cvprv%2Cmime%2Cns%2Cgir%2Cclen%2Cdur%2Clmt&lsparams=mh%2Cmm%2Cmn%2Cms%2Cmv%2Cmvi%2Cpl%2Cinitcwndbps&lsig=AG3C_xAwRgIhAKadP8fDQ2CVlaRLA77MmknN7va9SB7732Rgm3UkpxlMAiEA4zcIRG8YB424s1ydIyNQMQD5n4R_FbVCec4BftSZLcU%3D&sig=AOq0QJ8wRgIhAP8PZUiFVBQxQSIqHL8QnD_2feM1klNwcjTbz9a3LXVwAiEAlfSXLC3rPsCcQvlyEx5NINy31QXNlP2ioracaXQuoBM=", "width": null, "ext": "m4a", "vcodec": "none", "acodec": "mp4a.40.2", "abr": 129.504, "downloader_options": {"http_chunk_size": 10485760}, "container": "m4a_dash", "format": "140 - audio only (tiny)", "protocol": "https", "http_headers": {"User-Agent": "Mozilla/5.0 (Windows NT 10.0; Win64; x64) AppleWebKit/537.36 (KHTML, like Gecko) Chrome/70.0.3538.116 Safari/537.36", "Accept-Charset": "ISO-8859-1,utf-8;q=0.7,*;q=0.7", "Accept": "text/html,application/xhtml+xml,application/xml;q=0.9,*/*;q=0.8", "Accept-Encoding": "gzip, deflate", "Accept-Language": "en-us,en;q=0.5"}}, {"asr": 48000, "filesize": 2924764, "format_id": "251", "format_note": "tiny", "fps": null, "height": null, "quality": 0, "tbr": 134.409, "url": "https://rr5---sn-0opoxu-ihvr.googlevideo.com/videoplayback?expire=1670718318&ei=Dc-UY_GtPM-AsfIPuty4-AM&ip=189.173.225.87&id=o-AN502JbXx5gBx12bXj-eR-u8qZxAKw-nBrWZ3dt56oz9&itag=251&source=youtube&requiressl=yes&mh=Hg&mm=31%2C29&mn=sn-0opoxu-ihvr%2Csn-q4flrnsk&ms=au%2Crdu&mv=m&mvi=5&pl=24&pcm2=yes&initcwndbps=792500&vprv=1&mime=audio%2Fwebm&ns=0rfghrVTY7FJYMrm_ilQ2zwJ&gir=yes&clen=2924764&dur=174.081&lmt=1573658934500363&mt=1670696477&fvip=2&keepalive=yes&fexp=24001373%2C24007246&c=WEB&txp=1311222&n=CFYFrCNeVKvzRet3t&sparams=expire%2Cei%2Cip%2Cid%2Citag%2Csource%2Crequiressl%2Cpcm2%2Cvprv%2Cmime%2Cns%2Cgir%2Cclen%2Cdur%2Clmt&lsparams=mh%2Cmm%2Cmn%2Cms%2Cmv%2Cmvi%2Cpl%2Cinitcwndbps&lsig=AG3C_xAwRAIgFUyvp5ujf3Dg2cEZhHCqwffLjE7X8FgAooEAXmW5zooCIEiaPXpzHqfya34_raqj1bYGSjLy-3rtk4BUQD6dHG-8&sig=AOq0QJ8wRgIhANoT3D8JtIkSc5iHUWmbZHfZDNRZ4assC8weNgjzrkM3AiEA4Q0Xq7TGpa1HJk0DHYZpsH1oNbRpD6tYE0tgMIvGMNw=", "width": null, "ext": "webm", "vcodec": "none", "acodec": "opus", "abr": 134.409, "downloader_options": {"http_chunk_size": 10485760}, "container": "webm_dash", "format": "251 - audio only (tiny)", "protocol": "https", "http_headers": {"User-Agent": "Mozilla/5.0 (Windows NT 10.0; Win64; x64) AppleWebKit/537.36 (KHTML, like Gecko) Chrome/70.0.3538.116 Safari/537.36", "Accept-Charset": "ISO-8859-1,utf-8;q=0.7,*;q=0.7", "Accept": "text/html,application/xhtml+xml,application/xml;q=0.9,*/*;q=0.8", "Accept-Encoding": "gzip, deflate", "Accept-Language": "en-us,en;q=0.5"}}, {"asr": null, "filesize": 337696, "format_id": "160", "format_note": "144p", "fps": 30, "height": 144, "quality": 0, "tbr": 15.529, "url": "https://rr5---sn-0opoxu-ihvr.googlevideo.com/videoplayback?expire=1670718318&ei=Dc-UY_GtPM-AsfIPuty4-AM&ip=189.173.225.87&id=o-AN502JbXx5gBx12bXj-eR-u8qZxAKw-nBrWZ3dt56oz9&itag=160&aitags=133%2C134%2C135%2C160%2C242%2C243%2C244%2C278&source=youtube&requiressl=yes&mh=Hg&mm=31%2C29&mn=sn-0opoxu-ihvr%2Csn-q4flrnsk&ms=au%2Crdu&mv=m&mvi=5&pl=24&pcm2=yes&initcwndbps=792500&vprv=1&mime=video%2Fmp4&ns=0rfghrVTY7FJYMrm_ilQ2zwJ&gir=yes&clen=337696&dur=173.966&lmt=1573659050751775&mt=1670696477&fvip=2&keepalive=yes&fexp=24001373%2C24007246&c=WEB&txp=1316222&n=CFYFrCNeVKvzRet3t&sparams=expire%2Cei%2Cip%2Cid%2Caitags%2Csource%2Crequiressl%2Cpcm2%2Cvprv%2Cmime%2Cns%2Cgir%2Cclen%2Cdur%2Clmt&lsparams=mh%2Cmm%2Cmn%2Cms%2Cmv%2Cmvi%2Cpl%2Cinitcwndbps&lsig=AG3C_xAwRgIhAIAU0EWy5TlyaoYhwdGbsV4la4vGRUPQyDQ_8RJ3M7_AAiEAmOTJ-EKAVGUcBemp8ZHgIgP1XSucyPy-yjfICvfTs8I%3D&sig=AOq0QJ8wRAIgCAqyJmQBAIGviVk8H4hkpXJJUc3emvByvxoyiM9LdxcCIFcmeq5eWRE1m8BIr6ojhr319UBvWmNy85bibl_rnNdb", "width": 192, "ext": "mp4", "vcodec": "avc1.4d400c", "acodec": "none", "vbr": 15.529, "downloader_options": {"http_chunk_size": 10485760}, "container": "mp4_dash", "format": "160 - 192x144 (144p)", "protocol": "https", "http_headers": {"User-Agent": "Mozilla/5.0 (Windows NT 10.0; Win64; x64) AppleWebKit/537.36 (KHTML, like Gecko) Chrome/70.0.3538.116 Safari/537.36", "Accept-Charset": "ISO-8859-1,utf-8;q=0.7,*;q=0.7", "Accept": "text/html,application/xhtml+xml,application/xml;q=0.9,*/*;q=0.8", "Accept-Encoding": "gzip, deflate", "Accept-Language": "en-us,en;q=0.5"}}, {"asr": null, "filesize": 356506, "format_id": "278", "format_note": "144p", "fps": 30, "height": 144, "quality": 0, "tbr": 16.394, "url": "https://rr5---sn-0opoxu-ihvr.googlevideo.com/videoplayback?expire=1670718318&ei=Dc-UY_GtPM-AsfIPuty4-AM&ip=189.173.225.87&id=o-AN502JbXx5gBx12bXj-eR-u8qZxAKw-nBrWZ3dt56oz9&itag=278&aitags=133%2C134%2C135%2C160%2C242%2C243%2C244%2C278&source=youtube&requiressl=yes&mh=Hg&mm=31%2C29&mn=sn-0opoxu-ihvr%2Csn-q4flrnsk&ms=au%2Crdu&mv=m&mvi=5&pl=24&pcm2=yes&initcwndbps=792500&vprv=1&mime=video%2Fwebm&ns=0rfghrVTY7FJYMrm_ilQ2zwJ&gir=yes&clen=356506&dur=173.967&lmt=1573659058987691&mt=1670696477&fvip=2&keepalive=yes&fexp=24001373%2C24007246&c=WEB&txp=1316222&n=CFYFrCNeVKvzRet3t&sparams=expire%2Cei%2Cip%2Cid%2Caitags%2Csource%2Crequiressl%2Cpcm2%2Cvprv%2Cmime%2Cns%2Cgir%2Cclen%2Cdur%2Clmt&lsparams=mh%2Cmm%2Cmn%2Cms%2Cmv%2Cmvi%2Cpl%2Cinitcwndbps&lsig=AG3C_xAwRQIhAJEkNMDR7hTOMBvKxfnOdkiMeUMlZzxTm9a96VjXACkqAiANgvXjVE-JhX_fTriT2mGiGXizM_0JAR_xtnrtX0Xu7g%3D%3D&sig=AOq0QJ8wRgIhANPmcPHSZfjC2mePLhXFdReaQTHnzHwfqDPC3Hmd_xXAAiEAl-XenUiPbHnaJ7Gln5HmViotXpM-hDYSH25fHuEp2dM=", "width": 192, "ext": "webm", "vcodec": "vp9", "acodec": "none", "vbr": 16.394, "downloader_options": {"http_chunk_size": 10485760}, "container": "webm_dash", "format": "278 - 192x144 (144p)", "protocol": "https", "http_headers": {"User-Agent": "Mozilla/5.0 (Windows NT 10.0; Win64; x64) AppleWebKit/537.36 (KHTML, like Gecko) Chrome/70.0.3538.116 Safari/537.36", "Accept-Charset": "ISO-8859-1,utf-8;q=0.7,*;q=0.7", "Accept": "text/html,application/xhtml+xml,application/xml;q=0.9,*/*;q=0.8", "Accept-Encoding": "gzip, deflate", "Accept-Language": "en-us,en;q=0.5"}}, {"asr": null, "filesize": 393330, "format_id": "242", "format_note": "240p", "fps": 30, "height": 240, "quality": 1, "tbr": 18.087, "url": "https://rr5---sn-0opoxu-ihvr.googlevideo.com/videoplayback?expire=1670718318&ei=Dc-UY_GtPM-AsfIPuty4-AM&ip=189.173.225.87&id=o-AN502JbXx5gBx12bXj-eR-u8qZxAKw-nBrWZ3dt56oz9&itag=242&aitags=133%2C134%2C135%2C160%2C242%2C243%2C244%2C278&source=youtube&requiressl=yes&mh=Hg&mm=31%2C29&mn=sn-0opoxu-ihvr%2Csn-q4flrnsk&ms=au%2Crdu&mv=m&mvi=5&pl=24&pcm2=yes&initcwndbps=792500&vprv=1&mime=video%2Fwebm&ns=0rfghrVTY7FJYMrm_ilQ2zwJ&gir=yes&clen=393330&dur=173.967&lmt=1573659058981582&mt=1670696477&fvip=2&keepalive=yes&fexp=24001373%2C24007246&c=WEB&txp=1316222&n=CFYFrCNeVKvzRet3t&sparams=expire%2Cei%2Cip%2Cid%2Caitags%2Csource%2Crequiressl%2Cpcm2%2Cvprv%2Cmime%2Cns%2Cgir%2Cclen%2Cdur%2Clmt&lsparams=mh%2Cmm%2Cmn%2Cms%2Cmv%2Cmvi%2Cpl%2Cinitcwndbps&lsig=AG3C_xAwRQIhANt9ahETd7pp4Qb1FfBvmB-wugU5koLX4RS_w3ShLsprAiAlK61L4XwSGp3L9SW8ghqVZKWoTVDQh6UzR056q8znBA%3D%3D&sig=AOq0QJ8wRgIhAIDeZFC0PZoIAJeNY-GEqKbe6qOYOvomnWL3hEke4wn2AiEAok3GsYABM4ePvh2HFS9gtsrzc7E0hDq9A0l5E-1G3g0=", "width": 320, "ext": "webm", "vcodec": "vp9", "acodec": "none", "vbr": 18.087, "downloader_options": {"http_chunk_size": 10485760}, "container": "webm_dash", "format": "242 - 320x240 (240p)", "protocol": "https", "http_headers": {"User-Agent": "Mozilla/5.0 (Windows NT 10.0; Win64; x64) AppleWebKit/537.36 (KHTML, like Gecko) Chrome/70.0.3538.116 Safari/537.36", "Accept-Charset": "ISO-8859-1,utf-8;q=0.7,*;q=0.7", "Accept": "text/html,application/xhtml+xml,application/xml;q=0.9,*/*;q=0.8", "Accept-Encoding": "gzip, deflate", "Accept-Language": "en-us,en;q=0.5"}}, {"asr": null, "filesize": 514925, "format_id": "133", "format_note": "240p", "fps": 30, "height": 240, "quality": 1, "tbr": 23.679, "url": "https://rr5---sn-0opoxu-ihvr.googlevideo.com/videoplayback?expire=1670718318&ei=Dc-UY_GtPM-AsfIPuty4-AM&ip=189.173.225.87&id=o-AN502JbXx5gBx12bXj-eR-u8qZxAKw-nBrWZ3dt56oz9&itag=133&aitags=133%2C134%2C135%2C160%2C242%2C243%2C244%2C278&source=youtube&requiressl=yes&mh=Hg&mm=31%2C29&mn=sn-0opoxu-ihvr%2Csn-q4flrnsk&ms=au%2Crdu&mv=m&mvi=5&pl=24&pcm2=yes&initcwndbps=792500&vprv=1&mime=video%2Fmp4&ns=0rfghrVTY7FJYMrm_ilQ2zwJ&gir=yes&clen=514925&dur=173.966&lmt=1573659050791903&mt=1670696477&fvip=2&keepalive=yes&fexp=24001373%2C24007246&c=WEB&txp=1316222&n=CFYFrCNeVKvzRet3t&sparams=expire%2Cei%2Cip%2Cid%2Caitags%2Csource%2Crequiressl%2Cpcm2%2Cvprv%2Cmime%2Cns%2Cgir%2Cclen%2Cdur%2Clmt&lsparams=mh%2Cmm%2Cmn%2Cms%2Cmv%2Cmvi%2Cpl%2Cinitcwndbps&lsig=AG3C_xAwRAIgZNV9btrQGV4ZNY6eCtW-tqPy6zlB5hLnfKFwW3VRIVoCIEE9Uj-7w8Gp_fR83i-YuwpB-UbPwtdkY7utAck4I4A4&sig=AOq0QJ8wRAIgSe_5uUuMKHz5j72SUWiCIxcsGyPxbYA-ICFaj06snV8CIE548x4sMyaTdL6F8uup9dV8A2CXlUbZPt96SanDx0Uu", "width": 320, "ext": "mp4", "vcodec": "avc1.4d400d", "acodec": "none", "vbr": 23.679, "downloader_options": {"http_chunk_size": 10485760}, "container": "mp4_dash", "format": "133 - 320x240 (240p)", "protocol": "https", "http_headers": {"User-Agent": "Mozilla/5.0 (Windows NT 10.0; Win64; x64) AppleWebKit/537.36 (KHTML, like Gecko) Chrome/70.0.3538.116 Safari/537.36", "Accept-Charset": "ISO-8859-1,utf-8;q=0.7,*;q=0.7", "Accept": "text/html,application/xhtml+xml,application/xml;q=0.9,*/*;q=0.8", "Accept-Encoding": "gzip, deflate", "Accept-Language": "en-us,en;q=0.5"}}, {"asr": null, "filesize": 471008, "format_id": "243", "format_note": "360p", "fps": 30, "height": 360, "quality": 2, "tbr": 21.659, "url": "https://rr5---sn-0opoxu-ihvr.googlevideo.com/videoplayback?expire=1670718318&ei=Dc-UY_GtPM-AsfIPuty4-AM&ip=189.173.225.87&id=o-AN502JbXx5gBx12bXj-eR-u8qZxAKw-nBrWZ3dt56oz9&itag=243&aitags=133%2C134%2C135%2C160%2C242%2C243%2C244%2C278&source=youtube&requiressl=yes&mh=Hg&mm=31%2C29&mn=sn-0opoxu-ihvr%2Csn-q4flrnsk&ms=au%2Crdu&mv=m&mvi=5&pl=24&pcm2=yes&initcwndbps=792500&vprv=1&mime=video%2Fwebm&ns=0rfghrVTY7FJYMrm_ilQ2zwJ&gir=yes&clen=471008&dur=173.967&lmt=1573659059004818&mt=1670696477&fvip=2&keepalive=yes&fexp=24001373%2C24007246&c=WEB&txp=1316222&n=CFYFrCNeVKvzRet3t&sparams=expire%2Cei%2Cip%2Cid%2Caitags%2Csource%2Crequiressl%2Cpcm2%2Cvprv%2Cmime%2Cns%2Cgir%2Cclen%2Cdur%2Clmt&lsparams=mh%2Cmm%2Cmn%2Cms%2Cmv%2Cmvi%2Cpl%2Cinitcwndbps&lsig=AG3C_xAwRQIhAJvcu7waRqDgPyZaQOXlhKqIDEdG9OnxBN6ILsjo-cf8AiAw170qhjpC2ZxxvCYd8BDhdSMkEXr16mSHgWr2vyd21w%3D%3D&sig=AOq0QJ8wRQIgB7RlgVvSg4J54GeVfWXKXJhEWr74DuhEhEt_prUtwTUCIQCa5QAX0ovW3DzFFjZ_TPFZ21HbxjfpRXVq3bwlH7e-pQ==", "width": 480, "ext": "webm", "vcodec": "vp9", "acodec": "none", "vbr": 21.659, "downloader_options": {"http_chunk_size": 10485760}, "container": "webm_dash", "format": "243 - 480x360 (360p)", "protocol": "https", "http_headers": {"User-Agent": "Mozilla/5.0 (Windows NT 10.0; Win64; x64) AppleWebKit/537.36 (KHTML, like Gecko) Chrome/70.0.3538.116 Safari/537.36", "Accept-Charset": "ISO-8859-1,utf-8;q=0.7,*;q=0.7", "Accept": "text/html,application/xhtml+xml,application/xml;q=0.9,*/*;q=0.8", "Accept-Encoding": "gzip, deflate", "Accept-Language": "en-us,en;q=0.5"}}, {"asr": null, "filesize": 704759, "format_id": "134", "format_note": "360p", "fps": 30, "height": 360, "quality": 2, "tbr": 32.409, "url": "https://rr5---sn-0opoxu-ihvr.googlevideo.com/videoplayback?expire=1670718318&ei=Dc-UY_GtPM-AsfIPuty4-AM&ip=189.173.225.87&id=o-AN502JbXx5gBx12bXj-eR-u8qZxAKw-nBrWZ3dt56oz9&itag=134&aitags=133%2C134%2C135%2C160%2C242%2C243%2C244%2C278&source=youtube&requiressl=yes&mh=Hg&mm=31%2C29&mn=sn-0opoxu-ihvr%2Csn-q4flrnsk&ms=au%2Crdu&mv=m&mvi=5&pl=24&pcm2=yes&initcwndbps=792500&vprv=1&mime=video%2Fmp4&ns=0rfghrVTY7FJYMrm_ilQ2zwJ&gir=yes&clen=704759&dur=173.966&lmt=1573659050754266&mt=1670696477&fvip=2&keepalive=yes&fexp=24001373%2C24007246&c=WEB&txp=1316222&n=CFYFrCNeVKvzRet3t&sparams=expire%2Cei%2Cip%2Cid%2Caitags%2Csource%2Crequiressl%2Cpcm2%2Cvprv%2Cmime%2Cns%2Cgir%2Cclen%2Cdur%2Clmt&lsparams=mh%2Cmm%2Cmn%2Cms%2Cmv%2Cmvi%2Cpl%2Cinitcwndbps&lsig=AG3C_xAwRQIgJas8Gv5aiNK18TcbsQd6McxPBkZ-syqGg-XboDuOO6MCIQCKSMzb51sA_O4hOOCFv3e2WkP_IG5_d6CAJ88JDDjwKw%3D%3D&sig=AOq0QJ8wRgIhANt8UoJYtREBFJCNwUWnI0XyCguUQjI-R7kAVdXSUjwOAiEAs8xb20B4bks5JDI0K8pHSuHKuLigsiKPgIN0C5qOf-c=", "width": 480, "ext": "mp4", "vcodec": "avc1.4d401e", "acodec": "none", "vbr": 32.409, "downloader_options": {"http_chunk_size": 10485760}, "container": "mp4_dash", "format": "134 - 480x360 (360p)", "protocol": "https", "http_headers": {"User-Agent": "Mozilla/5.0 (Windows NT 10.0; Win64; x64) AppleWebKit/537.36 (KHTML, like Gecko) Chrome/70.0.3538.116 Safari/537.36", "Accept-Charset": "ISO-8859-1,utf-8;q=0.7,*;q=0.7", "Accept": "text/html,application/xhtml+xml,application/xml;q=0.9,*/*;q=0.8", "Accept-Encoding": "gzip, deflate", "Accept-Language": "en-us,en;q=0.5"}}, {"asr": null, "filesize": 620089, "format_id": "244", "format_note": "480p", "fps": 30, "height": 480, "quality": 3, "tbr": 28.515, "url": "https://rr5---sn-0opoxu-ihvr.googlevideo.com/videoplayback?expire=1670718318&ei=Dc-UY_GtPM-AsfIPuty4-AM&ip=189.173.225.87&id=o-AN502JbXx5gBx12bXj-eR-u8qZxAKw-nBrWZ3dt56oz9&itag=244&aitags=133%2C134%2C135%2C160%2C242%2C243%2C244%2C278&source=youtube&requiressl=yes&mh=Hg&mm=31%2C29&mn=sn-0opoxu-ihvr%2Csn-q4flrnsk&ms=au%2Crdu&mv=m&mvi=5&pl=24&pcm2=yes&initcwndbps=792500&vprv=1&mime=video%2Fwebm&ns=0rfghrVTY7FJYMrm_ilQ2zwJ&gir=yes&clen=620089&dur=173.967&lmt=1573659058976309&mt=1670696477&fvip=2&keepalive=yes&fexp=24001373%2C24007246&c=WEB&txp=1316222&n=CFYFrCNeVKvzRet3t&sparams=expire%2Cei%2Cip%2Cid%2Caitags%2Csource%2Crequiressl%2Cpcm2%2Cvprv%2Cmime%2Cns%2Cgir%2Cclen%2Cdur%2Clmt&lsparams=mh%2Cmm%2Cmn%2Cms%2Cmv%2Cmvi%2Cpl%2Cinitcwndbps&lsig=AG3C_xAwRgIhAI5SWrxyptCximqArSQX_Kj1DfS7Mx3ChmkPum7-Z9HPAiEAuqA_D-CKqbkrdJBdHwhJmoKH-PuY4OEMLurZvoy_7fo%3D&sig=AOq0QJ8wRQIgTik4P5BZLYyWT2S0h0UHBQpuOakc-lqSRPopqiHA5F0CIQDa8U4YLGAepVxyy5LxHTte7Tma9o7vS7ZjsnbU8WOgkA==", "width": 640, "ext": "webm", "vcodec": "vp9", "acodec": "none", "vbr": 28.515, "downloader_options": {"http_chunk_size": 10485760}, "container": "webm_dash", "format": "244 - 640x480 (480p)", "protocol": "https", "http_headers": {"User-Agent": "Mozilla/5.0 (Windows NT 10.0; Win64; x64) AppleWebKit/537.36 (KHTML, like Gecko) Chrome/70.0.3538.116 Safari/537.36", "Accept-Charset": "ISO-8859-1,utf-8;q=0.7,*;q=0.7", "Accept": "text/html,application/xhtml+xml,application/xml;q=0.9,*/*;q=0.8", "Accept-Encoding": "gzip, deflate", "Accept-Language": "en-us,en;q=0.5"}}, {"asr": null, "filesize": 1122417, "format_id": "135", "format_note": "480p", "fps": 30, "height": 480, "quality": 3, "tbr": 51.615, "url": "https://rr5---sn-0opoxu-ihvr.googlevideo.com/videoplayback?expire=1670718318&ei=Dc-UY_GtPM-AsfIPuty4-AM&ip=189.173.225.87&id=o-AN502JbXx5gBx12bXj-eR-u8qZxAKw-nBrWZ3dt56oz9&itag=135&aitags=133%2C134%2C135%2C160%2C242%2C243%2C244%2C278&source=youtube&requiressl=yes&mh=Hg&mm=31%2C29&mn=sn-0opoxu-ihvr%2Csn-q4flrnsk&ms=au%2Crdu&mv=m&mvi=5&pl=24&pcm2=yes&initcwndbps=792500&vprv=1&mime=video%2Fmp4&ns=0rfghrVTY7FJYMrm_ilQ2zwJ&gir=yes&clen=1122417&dur=173.966&lmt=1573659050758676&mt=1670696477&fvip=2&keepalive=yes&fexp=24001373%2C24007246&c=WEB&txp=1316222&n=CFYFrCNeVKvzRet3t&sparams=expire%2Cei%2Cip%2Cid%2Caitags%2Csource%2Crequiressl%2Cpcm2%2Cvprv%2Cmime%2Cns%2Cgir%2Cclen%2Cdur%2Clmt&lsparams=mh%2Cmm%2Cmn%2Cms%2Cmv%2Cmvi%2Cpl%2Cinitcwndbps&lsig=AG3C_xAwRAIgARdKgl-KnW-Goy2oKUd-chCg26ZjECqkqOpnCKf8zqsCIHgWTeYaTTq4S52nFKITwxP9n1qjtjn7JxquVde870Eu&sig=AOq0QJ8wRQIgMmM4qqrRTVElQdm0ACbBuevbshKWXidruMYmpZymh7sCIQDLZL_dWMaeZ6oVl2yrk9pAVTmj2NLmD8H5OSP5RXa4RQ==", "width": 640, "ext": "mp4", "vcodec": "avc1.4d401e", "acodec": "none", "vbr": 51.615, "downloader_options": {"http_chunk_size": 10485760}, "container": "mp4_dash", "format": "135 - 640x480 (480p)", "protocol": "https", "http_headers": {"User-Agent": "Mozilla/5.0 (Windows NT 10.0; Win64; x64) AppleWebKit/537.36 (KHTML, like Gecko) Chrome/70.0.3538.116 Safari/537.36", "Accept-Charset": "ISO-8859-1,utf-8;q=0.7,*;q=0.7", "Accept": "text/html,application/xhtml+xml,application/xml;q=0.9,*/*;q=0.8", "Accept-Encoding": "gzip, deflate", "Accept-Language": "en-us,en;q=0.5"}}, {"asr": 44100, "filesize": null, "format_id": "18", "format_note": "360p", "fps": 30, "height": 360, "quality": 2, "tbr": 160.964, "url": "https://rr5---sn-0opoxu-ihvr.googlevideo.com/videoplayback?expire=1670718318&ei=Dc-UY_GtPM-AsfIPuty4-AM&ip=189.173.225.87&id=o-AN502JbXx5gBx12bXj-eR-u8qZxAKw-nBrWZ3dt56oz9&itag=18&source=youtube&requiressl=yes&mh=Hg&mm=31%2C29&mn=sn-0opoxu-ihvr%2Csn-q4flrnsk&ms=au%2Crdu&mv=m&mvi=5&pl=24&pcm2=yes&initcwndbps=792500&vprv=1&mime=video%2Fmp4&ns=Jk_msH4RL2lfunx8tju7XMwJ&cnr=14&ratebypass=yes&dur=174.126&lmt=1657778388769999&mt=1670696477&fvip=2&fexp=24001373%2C24007246&c=WEB&txp=1318224&n=zpWjsjy-hQICguR5P&sparams=expire%2Cei%2Cip%2Cid%2Citag%2Csource%2Crequiressl%2Cpcm2%2Cvprv%2Cmime%2Cns%2Ccnr%2Cratebypass%2Cdur%2Clmt&lsparams=mh%2Cmm%2Cmn%2Cms%2Cmv%2Cmvi%2Cpl%2Cinitcwndbps&lsig=AG3C_xAwRQIhANSWcYbItl-NqB1djket1lXEeE3nFAV6DpbLtt5OurRqAiACHMUVLe9xwXvt85wloGdq5CZqt8OmZwYHVIYT15AWjw%3D%3D&sig=AOq0QJ8wRQIgYdprkimnXyFqHMTf4lvkPQMwbofKTDO2cloO2ZJXNy8CIQCe5prPDZ38RgQzmnQTUf9I3K2R11htq4CS6h0rSKU4yg==", "width": 480, "ext": "mp4", "vcodec": "avc1.42001E", "acodec": "mp4a.40.2", "format": "18 - 480x360 (360p)", "protocol": "https", "http_headers": {"User-Agent": "Mozilla/5.0 (Windows NT 10.0; Win64; x64) AppleWebKit/537.36 (KHTML, like Gecko) Chrome/70.0.3538.116 Safari/537.36", "Accept-Charset": "ISO-8859-1,utf-8;q=0.7,*;q=0.7", "Accept": "text/html,application/xhtml+xml,application/xml;q=0.9,*/*;q=0.8", "Accept-Encoding": "gzip, deflate", "Accept-Language": "en-us,en;q=0.5"}}], "thumbnails": [{"height": 94, "url": "https://i.ytimg.com/vi/X5KquK93ahI/hqdefault.jpg?sqp=-oaymwEbCKgBEF5IVfKriqkDDggBFQAAiEIYAXABwAEG&rs=AOn4CLBlA51fZkPpVk-vDQSnMOSP6twfjg", "width": 168, "resolution": "168x94", "id": "0"}, {"height": 110, "url": "https://i.ytimg.com/vi/X5KquK93ahI/hqdefault.jpg?sqp=-oaymwEbCMQBEG5IVfKriqkDDggBFQAAiEIYAXABwAEG&rs=AOn4CLAy6xg9AQTZRoQlPQXXdkimfplivA", "width": 196, "resolution": "196x110", "id": "1"}, {"height": 138, "url": "https://i.ytimg.com/vi/X5KquK93ahI/hqdefault.jpg?sqp=-oaymwEcCPYBEIoBSFXyq4qpAw4IARUAAIhCGAFwAcABBg==&rs=AOn4CLAavkMszo5fWj0Bg6hzY9HHvkFWXQ", "width": 246, "resolution": "246x138", "id": "2"}, {"height": 188, "url": "https://i.ytimg.com/vi/X5KquK93ahI/hqdefault.jpg?sqp=-oaymwEcCNACELwBSFXyq4qpAw4IARUAAIhCGAFwAcABBg==&rs=AOn4CLDb0k8kIc1RwyOWbLSoVEyjNtKw_w", "width": 336, "resolution": "336x188", "id": "3"}], "description": "el grupo que vale lo que pesa:pesado.", "upload_date": "20080924", "uploader": "nakito26", "uploader_id": "nakito26", "uploader_url": "http://www.youtube.com/user/nakito26", "channel_id": "UCPv-tvmTht1zTbWOyDAXojQ", "channel_url": "https://www.youtube.com/channel/UCPv-tvmTht1zTbWOyDAXojQ", "duration": 174, "view_count": 240689, "average_rating": null, "age_limit": 0, "webpage_url": "https://www.youtube.com/watch?v=X5KquK93ahI", "categories": ["Music"], "tags": ["pesado", "texano", "norte\u00f1o", "amor", "incondicional"], "is_live": null, "channel": "nakito26", "extractor": "youtube", "webpage_url_basename": "watch", "extractor_key": "Youtube", "playlist": null, "playlist_index": null, "thumbnail": "https://i.ytimg.com/vi/X5KquK93ahI/hqdefault.jpg?sqp=-oaymwEcCNACELwBSFXyq4qpAw4IARUAAIhCGAFwAcABBg==&rs=AOn4CLDb0k8kIc1RwyOWbLSoVEyjNtKw_w", "display_id": "X5KquK93ahI", "asr": 44100, "filesize": null, "format_id": "18", "format_note": "360p", "fps": 30, "height": 360, "quality": 2, "tbr": 160.964, "url": "https://rr5---sn-0opoxu-ihvr.googlevideo.com/videoplayback?expire=1670718318&ei=Dc-UY_GtPM-AsfIPuty4-AM&ip=189.173.225.87&id=o-AN502JbXx5gBx12bXj-eR-u8qZxAKw-nBrWZ3dt56oz9&itag=18&source=youtube&requiressl=yes&mh=Hg&mm=31%2C29&mn=sn-0opoxu-ihvr%2Csn-q4flrnsk&ms=au%2Crdu&mv=m&mvi=5&pl=24&pcm2=yes&initcwndbps=792500&vprv=1&mime=video%2Fmp4&ns=Jk_msH4RL2lfunx8tju7XMwJ&cnr=14&ratebypass=yes&dur=174.126&lmt=1657778388769999&mt=1670696477&fvip=2&fexp=24001373%2C24007246&c=WEB&txp=1318224&n=zpWjsjy-hQICguR5P&sparams=expire%2Cei%2Cip%2Cid%2Citag%2Csource%2Crequiressl%2Cpcm2%2Cvprv%2Cmime%2Cns%2Ccnr%2Cratebypass%2Cdur%2Clmt&lsparams=mh%2Cmm%2Cmn%2Cms%2Cmv%2Cmvi%2Cpl%2Cinitcwndbps&lsig=AG3C_xAwRQIhANSWcYbItl-NqB1djket1lXEeE3nFAV6DpbLtt5OurRqAiACHMUVLe9xwXvt85wloGdq5CZqt8OmZwYHVIYT15AWjw%3D%3D&sig=AOq0QJ8wRQIgYdprkimnXyFqHMTf4lvkPQMwbofKTDO2cloO2ZJXNy8CIQCe5prPDZ38RgQzmnQTUf9I3K2R11htq4CS6h0rSKU4yg==", "width": 480, "ext": "mp4", "vcodec": "avc1.42001E", "acodec": "mp4a.40.2", "format": "18 - 480x360 (360p)", "protocol": "https", "http_headers": {"User-Agent": "Mozilla/5.0 (Windows NT 10.0; Win64; x64) AppleWebKit/537.36 (KHTML, like Gecko) Chrome/70.0.3538.116 Safari/537.36", "Accept-Charset": "ISO-8859-1,utf-8;q=0.7,*;q=0.7", "Accept": "text/html,application/xhtml+xml,application/xml;q=0.9,*/*;q=0.8", "Accept-Encoding": "gzip, deflate", "Accept-Language": "en-us,en;q=0.5"}, "fulltitle": "pesado-amor incondicional", "_filename": "pesado-amor incondicional-X5KquK93ahI.mp4"}